pymodaq_pid_models/__init__.py
pymodaq_pid_models/utils.py
pymodaq_pid_models/version.py
pymodaq_pid_models/models/PIDModelMichelsonDemo.py
pymodaq_pid_models/models/PIDModelMock.py
pymodaq_pid_models/models/__init__.py
pymodaq_pid_models-0.0.4.dist-info/LICENSE
pymodaq_pid_models-0.0.4.dist-info/METADATA
pymodaq_pid_models-0.0.4.dist-info/WHEEL
pymodaq_pid_models-0.0.4.dist-info/top_level.txt
pymodaq_pid_models-0.0.4.dist-info/RECORD
